<annotation>
	<folder>train2014</folder>
	<filename>IMG_3541.jpg</filename>
	<path>F:\处理病害数据集\images\train2014\IMG_3541.jpg</path>
	<source>
		<database>Unknown</database>
	</source>
	<size>
		<width>4032</width>
		<height>3024</height>
		<depth>3</depth>
	</size>
	<segmented>0</segmented>
	<object>
		<name>chihuo_high</name>
		<pose>Unspecified</pose>
		<truncated>0</truncated>
		<difficult>0</difficult>
		<bndbox>
			<xmin>2244</xmin>
			<ymin>921</ymin>
			<xmax>3875</xmax>
			<ymax>1980</ymax>
		</bndbox>
	</object>
	<object>
		<name>chihuo_high</name>
		<pose>Unspecified</pose>
		<truncated>0</truncated>
		<difficult>0</difficult>
		<bndbox>
			<xmin>2287</xmin>
			<ymin>1584</ymin>
			<xmax>3400</xmax>
			<ymax>2230</ymax>
		</bndbox>
	</object>
	<object>
		<name>chihuo_low</name>
		<pose>Unspecified</pose>
		<truncated>0</truncated>
		<difficult>0</difficult>
		<bndbox>
			<xmin>6</xmin>
			<ymin>1337</ymin>
			<xmax>2128</xmax>
			<ymax>2462</ymax>
		</bndbox>
	</object>
	<object>
		<name>chihuo_high</name>
		<pose>Unspecified</pose>
		<truncated>0</truncated>
		<difficult>0</difficult>
		<bndbox>
			<xmin>1369</xmin>
			<ymin>684</ymin>
			<xmax>2106</xmax>
			<ymax>1059</ymax>
		</bndbox>
	</object>
	<object>
		<name>chihuo_low</name>
		<pose>Unspecified</pose>
		<truncated>0</truncated>
		<difficult>0</difficult>
		<bndbox>
			<xmin>1309</xmin>
			<ymin>540</ymin>
			<xmax>2272</xmax>
			<ymax>2521</ymax>
		</bndbox>
	</object>
</annotation>
